publica/__init__.py
publica/__main__.py
publica-0.0.0.dist-info/LICENSE
publica-0.0.0.dist-info/METADATA
publica-0.0.0.dist-info/WHEEL
publica-0.0.0.dist-info/top_level.txt
publica-0.0.0.dist-info/RECORD
